concussion/__init__.py
concussion/__main__.py
concussion/based.py
concussion/cursed_path.py
concussion/fs_locals.py
concussion/repl.py
concussion/shell_builtins.py
concussion/shell_state.py
concussion/stoppable_thread.py
concussion-0.2.2.dist-info/LICENSE
concussion-0.2.2.dist-info/METADATA
concussion-0.2.2.dist-info/WHEEL
concussion-0.2.2.dist-info/entry_points.txt
concussion-0.2.2.dist-info/RECORD
