Metadata-Version: 2.1
Name: concussion
Version: 0.2.2
Summary: It's kinda like Bash except it causes severe brain damage because it's actually a Python REPL.
Home-page: https://github.com/MaddyGuthridge/concussion
License: MIT
Author: Maddy Guthridge
Author-email: hello@maddyguthridge.com
Requires-Python: >=3.11,<4.0
Classifier: License :: OSI Approved :: MIT License
Classifier: Programming Language :: Python :: 3
Classifier: Programming Language :: Python :: 3.11
Classifier: Programming Language :: Python :: 3.12
Project-URL: Bug Tracker, https://github.com/MaddyGuthridge/concussion/issues
Project-URL: Online Documentation, https://github.com/MaddyGuthridge/concussion
Project-URL: Repository, https://github.com/MaddyGuthridge/concussion
